Metadata-Version: 1.0
Name: distb-probability
Version: 0.1
Summary: Gaussian_Binomial distributions
Home-page: UNKNOWN
Author: UNKNOWN
Author-email: UNKNOWN
License: UNKNOWN
Platform: UNKNOWN
